datasette_insert_unsafe/__init__.py
datasette_insert_unsafe-0.1.dist-info/METADATA
datasette_insert_unsafe-0.1.dist-info/WHEEL
datasette_insert_unsafe-0.1.dist-info/entry_points.txt
datasette_insert_unsafe-0.1.dist-info/top_level.txt
datasette_insert_unsafe-0.1.dist-info/RECORD
