Metadata-Version: 2.1
Name: datasette-insert-unsafe
Version: 0.1
Summary: Unsafe permissions for datasette-insert - allows all actions without authentication
Home-page: https://github.com/simonw/datasette-insert-unsafe
Author: Simon Willison
License: Apache License, Version 2.0
Project-URL: Issues, https://github.com/simonw/datasette-insert-unsafe/issues
Project-URL: CI, https://github.com/simonw/datasette-insert-unsafe/actions
Project-URL: Changelog, https://github.com/simonw/datasette-insert-unsafe/releases
Platform: UNKNOWN
Requires-Dist: datasette
Requires-Dist: datasette-insert (>=0.6)
Provides-Extra: test
Requires-Dist: pytest ; extra == 'test'
Requires-Dist: pytest-asyncio ; extra == 'test'
Requires-Dist: httpx ; extra == 'test'
Requires-Dist: sqlite-utils ; extra == 'test'
